slurm_script/__init__.py
slurm_script/__main__.py
slurm_script/main.py
slurm_script-0.1.8.dist-info/entry_points.txt
slurm_script-0.1.8.dist-info/WHEEL
slurm_script-0.1.8.dist-info/METADATA
slurm_script-0.1.8.dist-info/RECORD
