Metadata-Version: 2.1
Name: slurm-script
Version: 0.1.8
Summary: Python Slurm script interface
Author: Kyoungseoun Chung
Author-email: kyoungseoun.chung@gmail.com
Requires-Python: >=3.7,<4.0
Classifier: Programming Language :: Python :: 3
Classifier: Programming Language :: Python :: 3.7
Classifier: Programming Language :: Python :: 3.8
Classifier: Programming Language :: Python :: 3.9
Classifier: Programming Language :: Python :: 3.10
